flux_config_tui/__init__.py
flux_config_tui/__main__.py
flux_config_tui/client.py
flux_config_tui/client_app.py
flux_config_tui/config.py
flux_config_tui/flux_config_tui.tcss
flux_config_tui/messages.py
flux_config_tui/providers.py
flux_config_tui/screens/__init__.py
flux_config_tui/screens/activate_launch.py
flux_config_tui/screens/app_settings.py
flux_config_tui/screens/display_size.py
flux_config_tui/screens/energy_saving.py
flux_config_tui/screens/firewall_rules.py
flux_config_tui/screens/fluxbenchd_rpc_modal.py
flux_config_tui/screens/fluxd_rpc_modal.py
flux_config_tui/screens/installation_progress.py
flux_config_tui/screens/launch.py
flux_config_tui/screens/loading.py
flux_config_tui/screens/log_viewer.py
flux_config_tui/screens/logs.py
flux_config_tui/screens/logs.tcss
flux_config_tui/screens/reconfigure.py
flux_config_tui/screens/reinstall.py
flux_config_tui/screens/settings.py
flux_config_tui/screens/setup.py
flux_config_tui/screens/shutdown.py
flux_config_tui/screens/start_fluxnode_modal.py
flux_config_tui/screens/system_metrics.py
flux_config_tui/screens/system_metrics.tcss
flux_config_tui/screens/upgrade.py
flux_config_tui/screens/upnp_mappings.py
flux_config_tui/widgets/__init__.py
flux_config_tui/widgets/action_state.py
flux_config_tui/widgets/benchmark_status.py
flux_config_tui/widgets/block_count.py
flux_config_tui/widgets/fluxbenchd_metrics.py
flux_config_tui/widgets/fluxd_metrics.py
flux_config_tui/widgets/fluxd_status.py
flux_config_tui/widgets/fluxos_metrics.py
flux_config_tui/widgets/label_switch.py
flux_config_tui/widgets/launchpad.py
flux_config_tui/widgets/no_network.py
flux_config_tui/widgets/online_indicator.py
flux_config_tui/widgets/progress_indicator.py
flux_config_tui/widgets/qr.py
flux_config_tui/widgets/rpc_indicator.py
flux_config_tui/widgets/service_metrics.py
flux_config_tui/widgets/spinner.py
flux_config_tui/widgets/system_load.py
flux_config_tui/widgets/system_resources.py
flux_config_tui-0.1.0.dist-info/WHEEL
flux_config_tui-0.1.0.dist-info/entry_points.txt
flux_config_tui-0.1.0.dist-info/METADATA
flux_config_tui-0.1.0.dist-info/RECORD
