Metadata-Version: 2.3
Name: flux-config-tui
Version: 0.1.0
Summary: Flux Node Configuration TUI Client
Author: David White
Author-email: David White <david@runonflux.io>
License: GPL-3.0-or-later
Classifier: Development Status :: 4 - Beta
Classifier: Environment :: Console
Classifier: Intended Audience :: System Administrators
Classifier: License :: OSI Approved :: GNU General Public License v3 or later (GPLv3+)
Classifier: Programming Language :: Python :: 3
Classifier: Programming Language :: Python :: 3.13
Classifier: Topic :: System :: Systems Administration
Classifier: Topic :: System :: Monitoring
Requires-Dist: flux-config-shared>=0.1.0
Requires-Dist: textual>=6.11.0,<7
Requires-Dist: textual-fspicker>=0.6.0
Requires-Dist: qrcode>=7.4.2,<8
Requires-Dist: pyperclip>=1.9.0,<2
Requires-Dist: setproctitle>=1.3.7,<1.4
Requires-Dist: yarl>=1.18.3
Requires-Dist: asyncssh>=2.22.0
Requires-Dist: websockets>=15.0.1,<16
Requires-Dist: toml>=0.10.2
Requires-Python: >=3.13, <4
